setup.py
django_hesab.egg-info/PKG-INFO
django_hesab.egg-info/SOURCES.txt
django_hesab.egg-info/dependency_links.txt
django_hesab.egg-info/not-zip-safe
django_hesab.egg-info/requires.txt
django_hesab.egg-info/top_level.txt
hesab/__init__.py
hesab/backends.py
hesab/fields.py
hesab/settings.py
hesab/utils.py